etiket_client/__init__.py
etiket_client/copy_dataset.py
etiket_client/exceptions.py
etiket_client/GUI/__init__.py
etiket_client/GUI/sync/__init__.py
etiket_client/GUI/sync/app.py
etiket_client/GUI/sync/models/__init__.py
etiket_client/GUI/sync/models/login_mgmt.py
etiket_client/GUI/sync/models/schema_mgmt.py
etiket_client/GUI/sync/models/scope_mgmt.py
etiket_client/GUI/sync/models/sync_def_scope.py
etiket_client/GUI/sync/models/sync_mgmt.py
etiket_client/GUI/sync/models/sync_proc_mgmt.py
etiket_client/GUI/sync/models/helpers/__init__.py
etiket_client/GUI/sync/models/helpers/pyqt_tcp_handler.py
etiket_client/GUI/sync/qml/__init__.py
etiket_client/GUI/sync/qml/login.qml
etiket_client/GUI/sync/qml/main.qml
etiket_client/GUI/sync/qml/settings_index.qml
etiket_client/GUI/sync/qml/icons/__init__.py
etiket_client/GUI/sync/qml/icons/app_icon.svg
etiket_client/GUI/sync/qml/icons/delete.svg
etiket_client/GUI/sync/qml/icons/info.svg
etiket_client/GUI/sync/qml/icons/logout.svg
etiket_client/GUI/sync/qml/icons/refresh.svg
etiket_client/GUI/sync/qml/settings_pages/__init__.py
etiket_client/GUI/sync/qml/settings_pages/scope_settings.qml
etiket_client/GUI/sync/qml/settings_pages/sync_add_new_source.qml
etiket_client/GUI/sync/qml/settings_pages/sync_settings.qml
etiket_client/GUI/sync/resources/__init__.py
etiket_client/GUI/sync/resources/resource_rc.py
etiket_client/GUI/sync/resources/icons/__init__.py
etiket_client/GUI/sync/resources/icons/app_icon.svg
etiket_client/GUI/sync/resources/icons/delete.svg
etiket_client/GUI/sync/resources/icons/logout.svg
etiket_client/local/__init__.py
etiket_client/local/database.py
etiket_client/local/exceptions.py
etiket_client/local/model.py
etiket_client/local/types.py
etiket_client/local/alembic/__init__.py
etiket_client/local/alembic/env.py
etiket_client/local/alembic/versions/05eeaf971b07_mail_is_not_unique_anymore.py
etiket_client/local/alembic/versions/155970a8159a_added_api_keys.py
etiket_client-0.2.54.dist-info/licenses/LICENCE
etiket_client-0.2.54.dist-info/METADATA
etiket_client-0.2.54.dist-info/WHEEL
etiket_client-0.2.54.dist-info/top_level.txt
etiket_client-0.2.54.dist-info/zip-safe
etiket_client-0.2.54.dist-info/RECORD
