Metadata-Version: 2.4
Name: etiket_client
Version: 0.2.54
Summary: A client to interact with the etiket web framework.
Author: QDrive team
Requires-Python: >=3.7
License-File: LICENCE
Requires-Dist: PyQt5>=5.15.0
Requires-Dist: SQLAlchemy>=2.0.0
Requires-Dist: alembic>=1.6.0
Requires-Dist: pydantic<3.0.0,>=2.5.0
Requires-Dist: requests>=2.2.0
Requires-Dist: tqdm>=4.64.0
Requires-Dist: urllib3<=2.0.6
Requires-Dist: tabulate>=0.8.0
Requires-Dist: filelock>=3.4.0
Requires-Dist: platformdirs>=4.0.0
Requires-Dist: psutil>=5.8.0
Requires-Dist: numpy>=1.16.0
Requires-Dist: PyYAML>=6.0.0
Requires-Dist: email-validator<=2.1.0
Requires-Dist: xarray<=0.20.2,>=0.15.0; python_version < "3.8"
Requires-Dist: h5py<=3.8.0,>=3.0.0; python_version < "3.8"
Requires-Dist: xarray>=0.20.2; python_version >= "3.8"
Requires-Dist: h5py>=3.8.0; python_version >= "3.8"
Requires-Dist: setproctitle>=1.3.3
Requires-Dist: python-dateutil>2.8.0
Requires-Dist: qcodes>0.35.0
Requires-Dist: semantic-version>=2.10.0
Requires-Dist: pywin32>=306; platform_system == "Windows"
Requires-Dist: watchdog>=4.0.0
Requires-Dist: requests_oauthlib>=2.0.0
Requires-Dist: prettytable>=3.12.0
Requires-Dist: regex>=2024.11.6
Dynamic: license-file
